azure_utils/__init__.py
azure_utils/common_code.py
azure_utils_test/__init__.py
azure_utils_test/common_code.py
azure_utils_test-1.0.0.dist-info/METADATA
azure_utils_test-1.0.0.dist-info/WHEEL
azure_utils_test-1.0.0.dist-info/top_level.txt
azure_utils_test-1.0.0.dist-info/RECORD
