Metadata-Version: 2.1
Name: azure-utils-test
Version: 1.0.0
Summary: Shared Python Azure Utils Code for use in FunctionApps
